fastapi_extras/__init__.py
fastapi_extras/databases/__init__.py
fastapi_extras/databases/redis.py
fastapi_extras/middlewares/__init__.py
fastapi_extras/middlewares/remove_cloud_trace_headers.py
fastapi_extras/middlewares/remove_path.py
fastapi_extras/orm/__init__.py
fastapi_extras/orm/sqlalchemy.py
fastapi_extras/security/__init__.py
fastapi_extras/security/auth.py
fastapi_ext_pkg-0.4.2.dist-info/METADATA
fastapi_ext_pkg-0.4.2.dist-info/WHEEL
fastapi_ext_pkg-0.4.2.dist-info/top_level.txt
fastapi_ext_pkg-0.4.2.dist-info/RECORD
