Metadata-Version: 2.2
Name: fastapi-ext-pkg
Version: 0.4.2
Summary: A well-tailored utility set for FastAPI.
Author-email: Dotz Developers <devs-dotz@dotz.com>
Project-URL: Repository, https://github.com/DotzInc/fastapi-ext-pkg
Keywords: fastapi,utilities
Classifier: Operating System :: OS Independent
Classifier: Programming Language :: Python :: 3 :: Only
Classifier: Programming Language :: Python :: 3.8
Classifier: Programming Language :: Python :: 3.9
Classifier: Programming Language :: Python :: 3.10
Classifier: Programming Language :: Python :: 3.11
Classifier: Programming Language :: Python :: 3.12
Classifier: Topic :: Internet
Classifier: Topic :: Software Development
Classifier: Intended Audience :: Developers
Classifier: License :: OSI Approved :: MIT License
Requires-Python: >=3.8
Requires-Dist: fastapi
Requires-Dist: httpx
